{"_id":"14sHrLj3Vns51uJ5","email":"intiv@yahoo.com","firstname":"Inti","idnumber":"0801-1996-12345","lastname":"Velásquez","services":["Cable","Agua"],"zone":"Residencial Urbana"}
{"email":"juany@yahoo.com","firstname":"Juany","idnumber":"0801-1997-12345","lastname":"Ramirez","services":["Cable","Agua"],"zone":"Comercial","_id":"2HDJrRxN0UadIWZN"}
{"email":"pity@gmail.com","firstname":"Miguel","idnumber":"0801-1991-45678","lastname":"Angel","services":["Cable","Agua"],"zone":"Comercial","_id":"8XoxVvxabQrOZl7e"}
{"_id":"EFziGyns7EPskIK5","email":"cesarfig@yahoo.com","firstname":"Cesar","idnumber":"0801-1997-54321","lastname":"Figueroa","services":["Cable","Agua"],"zone":"Residencial Urbana"}
{"_id":"PL4FwwMb4jeWF1Pi","email":"mariom@gmail.com","firstname":"Mario","idnumber":"0801-1960-02532","lastname":"Maldonado","services":["Agua"],"zone":"Rural"}
{"email":"alexyc@gmail.com","firstname":"Alexy","idnumber":"0801-1994-44555","lastname":"Cruz","services":["Cable"],"zone":"Rural","_id":"QDXzBTl68hhzK4Tz"}
{"_id":"r7jjSb8FR92B4rz9","email":"rgaldam@gmail.com","firstname":"Ricardo","idnumber":"0801-1997-85671","lastname":"Galdamez","services":["Cable"],"zone":"Residencial Urbana"}
